pygbm_urvinath/__init__.py
pygbm_urvinath/__main__.py
pygbm_urvinath/base_gbm.py
pygbm_urvinath/cli.py
pygbm_urvinath/gbm_simulator.py
pygbm_urvinath/test.py
pygbm_urvinath/version.py
pygbm_urvinath-0.0.0b1.dev0.dist-info/METADATA
pygbm_urvinath-0.0.0b1.dev0.dist-info/WHEEL
pygbm_urvinath-0.0.0b1.dev0.dist-info/entry_points.txt
pygbm_urvinath-0.0.0b1.dev0.dist-info/top_level.txt
pygbm_urvinath-0.0.0b1.dev0.dist-info/RECORD
