Metadata-Version: 2.4
Name: pygbm_urvinath
Version: 0.0.0b1.dev0
Summary: A Python package for simulating Geometric Brownian Motion.
Author-email: Your Name <your.email@example.com>, Boris <boris.bolliet@gmail.com>
Keywords: brownian,motion
Classifier: Development Status :: 4 - Beta
Classifier: Intended Audience :: Information Technology
Classifier: License :: OSI Approved :: MIT License
Classifier: Programming Language :: Python :: 3
Classifier: Topic :: Software Development :: Libraries
Requires-Python: >=3.9
Requires-Dist: numpy
Requires-Dist: pandas
Requires-Dist: argparse
